geoarrow/rust/compute/__init__.py
geoarrow/rust/compute/_compute.cpython-314-darwin.so
geoarrow/rust/compute/_compute.pyi
geoarrow/rust/compute/enums.py
geoarrow/rust/compute/py.typed
geoarrow/rust/compute/types.py
geoarrow_rust_compute-0.6.1.dist-info/METADATA
geoarrow_rust_compute-0.6.1.dist-info/WHEEL
geoarrow_rust_compute-0.6.1.dist-info/RECORD
